mcdp_format2_py/__init__.py
mcdp_format2_py/formatter.py
mcdp_format2_py/load.py
mcdp_format2_py/py.typed
mcdp_format2_py/schemas.py
mcdp_format2_py-2.17.2507141632.dist-info/METADATA
mcdp_format2_py-2.17.2507141632.dist-info/WHEEL
mcdp_format2_py-2.17.2507141632.dist-info/RECORD
