Metadata-Version: 2.3
Name: mcdp-format2-py
Version: 2.17.2507141632
Summary: Library for reading MCDP format 2 files
Author: Andrea Censi
Author-email: AndreaCensi@users.noreply.github.com
Classifier: Programming Language :: Python :: 2
Classifier: Programming Language :: Python :: 2.7
Classifier: Programming Language :: Python :: 3
Classifier: Programming Language :: Python :: 3.4
Classifier: Programming Language :: Python :: 3.5
Classifier: Programming Language :: Python :: 3.6
Classifier: Programming Language :: Python :: 3.7
Classifier: Programming Language :: Python :: 3.8
Classifier: Programming Language :: Python :: 3.9
Classifier: Programming Language :: Python :: 3.10
Classifier: Programming Language :: Python :: 3.11
Classifier: Programming Language :: Python :: 3.12
Classifier: Programming Language :: Python :: 3.13
Provides-Extra: test
Requires-Dist: cbor2 (>=5.0.0)
Requires-Dist: colorama (>=0.4.0)
Requires-Dist: ruamel.yaml (>=0.17.0)
